keyed_login/__init__.py
keyed_login/__main__.py
keyed_login/cli.py
keyed_login/core.py
keyed_login-0.1.2.dist-info/METADATA
keyed_login-0.1.2.dist-info/WHEEL
keyed_login-0.1.2.dist-info/entry_points.txt
keyed_login-0.1.2.dist-info/top_level.txt
keyed_login-0.1.2.dist-info/RECORD
