Metadata-Version: 2.4
Name: keyed-login
Version: 0.1.2
Summary: A client for logging into the keyed-extras package registry.
Requires-Python: >=3.11
Requires-Dist: requests>=2.32.3
Requires-Dist: rich>=14.0.0
Requires-Dist: typer>=0.15.4
